statsig_python_core-0.14.0.dist-info/METADATA
statsig_python_core-0.14.0.dist-info/WHEEL
statsig_python_core/__init__.py
statsig_python_core/data_store.py
statsig_python_core/error_boundary.py
statsig_python_core/observability_client.py
statsig_python_core/output_logger_provider.py
statsig_python_core/persistent_storage.py
statsig_python_core/py.typed
statsig_python_core/requirements.txt
statsig_python_core/statsig.py
statsig_python_core/statsig_python_core.abi3.so
statsig_python_core/statsig_python_core.pyi
statsig_python_core-0.14.0.dist-info/RECORD
