Metadata-Version: 2.4
Name: statsig_python_core
Version: 0.14.0
Classifier: Programming Language :: Rust
Classifier: Programming Language :: Python :: Implementation :: CPython
Classifier: Programming Language :: Python :: Implementation :: PyPy
Requires-Dist: requests
Requires-Dist: typing-extensions
Summary: Statsig Python bindings for the Statsig Core SDK.
Home-Page: https://statsig.com/
Author: Statsig, Daniel Loomb <daniel@statsig.com>
Author-email: Statsig, Daniel Loomb <daniel@statsig.com>
License: ISC
Requires-Python: >=3.7
Project-URL: homepage, https://statsig.com
Project-URL: documentation, https://docs.statsig.com/server-core/python-core
Project-URL: repository, https://github.com/statsig-io/statsig-server-core/tree/main/statsig-pyo3
Project-URL: changelog, https://github.com/statsig-io/statsig-server-core/releases
